client/__init__.py
clientsock-0.0.1.dist-info/METADATA
clientsock-0.0.1.dist-info/WHEEL
clientsock-0.0.1.dist-info/top_level.txt
clientsock-0.0.1.dist-info/RECORD
