Metadata-Version: 2.1
Name: clientsock
Version: 0.0.1
Summary: used for cloud development
Home-page: https://github.com/pypa/sampleproject
Author: FeedFall8
Author-email: FeedFall80@gmail.com
License: UNKNOWN
Platform: UNKNOWN
Classifier: Programming Language :: Python :: 3
Classifier: License :: OSI Approved :: MIT License
Classifier: Operating System :: OS Independent
Requires-Python: >=3.6
